secstructartist/__init__.py
secstructartist/artists/__init__.py
secstructartist/artists/abc.py
secstructartist/artists/helix.py
secstructartist/artists/loop.py
secstructartist/artists/sheet.py
secstructartist/interface/__init__.py
secstructartist/interface/artist.py
secstructartist/interface/artist_dssp.py
secstructartist/interface/funcs.py
secstructartist/utils/__init__.py
secstructartist/utils/utils.py
secstructartist-1.1.3.dist-info/LICENSE
secstructartist-1.1.3.dist-info/METADATA
secstructartist-1.1.3.dist-info/WHEEL
secstructartist-1.1.3.dist-info/top_level.txt
secstructartist-1.1.3.dist-info/RECORD
